AUTHORS.rst
CONTRIBUTING.rst
HISTORY.rst
LICENSE
MANIFEST.in
README.rst
setup.py
rui/__init__.py
rui/exceptions.py
rui/rui.py
rui.egg-info/PKG-INFO
rui.egg-info/SOURCES.txt
rui.egg-info/dependency_links.txt
rui.egg-info/not-zip-safe
rui.egg-info/top_level.txt