Metadata-Version: 1.0
Name: rui
Version: 0.8.0
Summary: An imperfect Python ECS
Home-page: https://github.com/timothyhahn/rui
Author: Timothy Hahn
Author-email: timyhahn@gmail.com
License: BSD
Keywords: rui
Platform: UNKNOWN
Classifier: Development Status :: 2 - Pre-Alpha
Classifier: Intended Audience :: Developers
Classifier: License :: OSI Approved :: BSD License
Classifier: Natural Language :: English
Classifier: Programming Language :: Python :: 2
Classifier: Programming Language :: Python :: 2.6
Classifier: Programming Language :: Python :: 2.7
Classifier: Programming Language :: Python :: 3
Classifier: Programming Language :: Python :: 3.3
